telebot_components/__init__.py
telebot_components/broadcast/__init__.py
telebot_components/broadcast/message_senders.py
telebot_components/broadcast/subscriber.py
telebot_components/constants/__init__.py
telebot_components/constants/emoji.py
telebot_components/constants/times.py
telebot_components/data/language_data.json
telebot_components/feedback/__init__.py
telebot_components/feedback/anti_spam.py
telebot_components/feedback/integration/__init__.py
telebot_components/feedback/integration/aux_feedback_handler.py
telebot_components/feedback/integration/interface.py
telebot_components/feedback/integration/trello.py
telebot_components/feedback/trello_integration.py
telebot_components/feedback/types.py
telebot_components/form/__init__.py
telebot_components/form/field.py
telebot_components/form/form.py
telebot_components/form/handler.py
telebot_components/form/helpers/__init__.py
telebot_components/form/helpers/calendar_keyboard.py
telebot_components/form/helpers/dynamic_enum.py
telebot_components/form/types.py
telebot_components/language.py
telebot_components/menu/__init__.py
telebot_components/menu/dynamic.py
telebot_components/menu/menu.py
telebot_components/py.typed
telebot_components/redis_utils/__init__.py
telebot_components/redis_utils/emulation.py
telebot_components/redis_utils/interface.py
telebot_components/stores/__init__.py
telebot_components/stores/banned_users.py
telebot_components/stores/category.py
telebot_components/stores/forum_topics.py
telebot_components/stores/generic.py
telebot_components/stores/language.py
telebot_components/stores/types.py
telebot_components/stores/user_group.py
telebot_components/stores/utils.py
telebot_components/utils/__init__.py
telebot_components/utils/airtable.py
telebot_components/utils/alerts.py
telebot_components/utils/diff.py
telebot_components/utils/secrets.py
telebot_components/utils/strings.py
telebot_components-0.16.3.dist-info/LICENSE
telebot_components-0.16.3.dist-info/METADATA
telebot_components-0.16.3.dist-info/WHEEL
telebot_components-0.16.3.dist-info/RECORD
