Metadata-Version: 2.1
Name: telebot-components
Version: 0.16.3
Summary: Framework/toolkit for building Telegram bots with telebot and redis
Home-page: https://github.com/bots-against-war/telebot-components
License: GPLv3
Author: Igor Vaiman
Author-email: gosha.vaiman@gmail.com
Requires-Python: >=3.10,<4.0
Classifier: License :: Other/Proprietary License
Classifier: Programming Language :: Python :: 3
Classifier: Programming Language :: Python :: 3.10
Classifier: Programming Language :: Python :: 3.11
Classifier: Programming Language :: Python :: 3.12
Requires-Dist: Pillow (>=10.0.1,<11.0.0)
Requires-Dist: aiohttp (>=3.12.15,<4.0.0)
Requires-Dist: async-lru (>=2.0.2,<3.0.0)
Requires-Dist: beautifulsoup4 (>=4.11.1,<5.0.0)
Requires-Dist: cryptography (>=44.0.1,<45.0.0)
Requires-Dist: diff-match-patch (>=20230430,<20230431)
Requires-Dist: markdown (>=3.4.1,<4.0.0)
Requires-Dist: markdownify (>=1.1.0,<2.0.0)
Requires-Dist: py-trello (>=0.18.0,<0.19.0)
Requires-Dist: pyairtable (>=1.5.0,<2.0.0)
Requires-Dist: pydantic (>=2.10.6,<3.0.0)
Requires-Dist: pytest-mock (>=3.7.0,<4.0.0)
Requires-Dist: redis (>=5.0.1,<6.0.0)
Requires-Dist: requests (>=2.32.4,<3.0.0)
Requires-Dist: ruamel.yaml (>=0.17.21,<0.18.0)
Requires-Dist: telebot-against-war (>=0.7.14,<0.8.0)
Requires-Dist: tenacity (>=8.1.0,<9.0.0)
Requires-Dist: toml (>=0.10.2,<0.11.0)
Requires-Dist: urllib3 (>=1.26.18,<2.0.0)
Project-URL: Repository, https://github.com/bots-against-war/telebot-components
